dualdb_memory/__init__.py
dualdb_memory/cli.py
dualdb_memory/manager.py
dualdb_memory/memory.py
dualdb_memory/store_json.py
dualdb_memory/store_sqlite.py
dualdb_memory/summarizer_base.py
dualdb_memory/summarizer_openai.py
dualdb_memory/summarizer_stub.py
dualdb_memory_plugin-1.1.3.dist-info/licenses/LICENSE
examples/__init__.py
examples/demo_basic.py
examples/demo_concurrent.py
examples/demo_full.py
examples/demo_openai.py
examples/demo_perf.py
examples/demo_stability.py
examples/demo_stress.py
dualdb_memory_plugin-1.1.3.dist-info/METADATA
dualdb_memory_plugin-1.1.3.dist-info/WHEEL
dualdb_memory_plugin-1.1.3.dist-info/entry_points.txt
dualdb_memory_plugin-1.1.3.dist-info/top_level.txt
dualdb_memory_plugin-1.1.3.dist-info/RECORD
