Metadata-Version: 2.4
Name: dualdb-memory-plugin
Version: 1.1.3
Summary: Lightweight AI dialogue memory rotation plugin with dual DB (JSON/SQLite) and pluggable summarizer
Home-page: https://github.com/YZXY6151/dualdb-memory-plugin
Author: YZXY6151
Author-email: yzxy6151@gmail.com
License: CC BY-NC-SA 4.0
Classifier: Programming Language :: Python :: 3
Classifier: License :: Free To Use But Restricted
Requires-Python: >=3.7
License-File: LICENSE
Dynamic: author
Dynamic: author-email
Dynamic: classifier
Dynamic: description
Dynamic: description-content-type
Dynamic: home-page
Dynamic: license
Dynamic: license-file
Dynamic: requires-python
Dynamic: summary
